{"errors":[],"warnings":["chunk styles [mini-css-extract-plugin]\nConflicting order between:\n * css ./node_modules/css-loader??ref--13-oneOf-1-1!./node_modules/postcss-loader/lib??postcss-3!./node_modules/sass-loader/dist/cjs.js??ref--13-oneOf-1-3!./src/components/footer/_footer.scss\n * css ./node_modules/css-loader??ref--13-oneOf-1-1!./node_modules/postcss-loader/lib??postcss-3!./node_modules/sass-loader/dist/cjs.js??ref--13-oneOf-1-3!./src/components/banner/_banner.scss","chunk styles [mini-css-extract-plugin]\nConflicting order between:\n * css ./node_modules/css-loader??ref--13-oneOf-1-1!./node_modules/postcss-loader/lib??postcss-3!./node_modules/sass-loader/dist/cjs.js??ref--13-oneOf-1-3!./src/components/banner/_banner.scss\n * css ./node_modules/css-loader??ref--13-oneOf-1-1!./node_modules/postcss-loader/lib??postcss-3!./node_modules/sass-loader/dist/cjs.js??ref--13-oneOf-1-3!./src/sass/styles.scss"],"namedChunkGroups":{"app":{"chunks":[7,1,0,2],"assets":["webpack-runtime-e60e1605439f07125112.js","webpack-runtime-e60e1605439f07125112.js.map","styles.e87c0813b95531becc0a.css","styles-88b82bbc715a19271275.js","styles-88b82bbc715a19271275.js.map","commons-7b304016bd7d0f692664.js","commons-7b304016bd7d0f692664.js.map","app-dfe13298b1cd8ed550c5.js","app-dfe13298b1cd8ed550c5.js.map"],"children":{},"childAssets":{}},"component---src-templates-article-template-js":{"chunks":[1,0,6],"assets":["styles.e87c0813b95531becc0a.css","styles-88b82bbc715a19271275.js","styles-88b82bbc715a19271275.js.map","commons-7b304016bd7d0f692664.js","commons-7b304016bd7d0f692664.js.map","component---src-templates-article-template-js-1615109b9953cb536e76.js","component---src-templates-article-template-js-1615109b9953cb536e76.js.map"],"children":{},"childAssets":{}},"component---src-pages-404-js":{"chunks":[1,0,3],"assets":["styles.e87c0813b95531becc0a.css","styles-88b82bbc715a19271275.js","styles-88b82bbc715a19271275.js.map","commons-7b304016bd7d0f692664.js","commons-7b304016bd7d0f692664.js.map","component---src-pages-404-js-a4a780b117839437aec4.js","component---src-pages-404-js-a4a780b117839437aec4.js.map"],"children":{},"childAssets":{}},"component---src-pages-index-js":{"chunks":[1,0,4],"assets":["styles.e87c0813b95531becc0a.css","styles-88b82bbc715a19271275.js","styles-88b82bbc715a19271275.js.map","commons-7b304016bd7d0f692664.js","commons-7b304016bd7d0f692664.js.map","component---src-pages-index-js-437a09c30261dbfbb8e3.js","component---src-pages-index-js-437a09c30261dbfbb8e3.js.map"],"children":{},"childAssets":{}},"component---src-pages-page-2-js":{"chunks":[1,0,5],"assets":["styles.e87c0813b95531becc0a.css","styles-88b82bbc715a19271275.js","styles-88b82bbc715a19271275.js.map","commons-7b304016bd7d0f692664.js","commons-7b304016bd7d0f692664.js.map","component---src-pages-page-2-js-4499af82bef6b62d8b4a.js","component---src-pages-page-2-js-4499af82bef6b62d8b4a.js.map"],"children":{},"childAssets":{}}},"assetsByChunkName":{"app":["webpack-runtime-e60e1605439f07125112.js","styles.e87c0813b95531becc0a.css","styles-88b82bbc715a19271275.js","commons-7b304016bd7d0f692664.js","app-dfe13298b1cd8ed550c5.js"],"component---src-templates-article-template-js":["styles.e87c0813b95531becc0a.css","styles-88b82bbc715a19271275.js","commons-7b304016bd7d0f692664.js","component---src-templates-article-template-js-1615109b9953cb536e76.js"],"component---src-pages-404-js":["styles.e87c0813b95531becc0a.css","styles-88b82bbc715a19271275.js","commons-7b304016bd7d0f692664.js","component---src-pages-404-js-a4a780b117839437aec4.js"],"component---src-pages-index-js":["styles.e87c0813b95531becc0a.css","styles-88b82bbc715a19271275.js","commons-7b304016bd7d0f692664.js","component---src-pages-index-js-437a09c30261dbfbb8e3.js"],"component---src-pages-page-2-js":["styles.e87c0813b95531becc0a.css","styles-88b82bbc715a19271275.js","commons-7b304016bd7d0f692664.js","component---src-pages-page-2-js-4499af82bef6b62d8b4a.js"]}}